imitateai/__init__.py
imitateai/modeling.py
imitateai/refinement.py
imitateai/common/__init__.py
imitateai/common/utils.py
imitateai/data/__init__.py
imitateai/data/demonstration.py
imitateai/examples/01_infer_reward_model.py
imitateai/examples/02_recursive_refinement.py
imitateai/irl/__init__.py
imitateai/irl/base.py
imitateai/irl/gail.py
imitateai/irl/maxent.py
imitateai/models/__init__.py
imitateai/models/reward_model.py
imitateai/rl/__init__.py
imitateai/rl/grpo_trainer.py
imitateai/rl/ppo_trainer.py
imitateai/tests/__init__.py
imitateai/tests/test_modeling.py
imitateai/tests/test_refinement.py
imitateai-0.1.0.dist-info/licenses/LICENSE
imitateai-0.1.0.dist-info/METADATA
imitateai-0.1.0.dist-info/WHEEL
imitateai-0.1.0.dist-info/top_level.txt
imitateai-0.1.0.dist-info/RECORD
