Metadata-Version: 2.4
Name: imitateai
Version: 0.1.0
Summary: Inverse Reinforcement Learning for LLMs. Infer rewards and refine models.
Author-email: Your Name <your@email.com>
Project-URL: Homepage, https://github.com/your-username/imitateai
Project-URL: Issues, https://github.com/your-username/imitateai/issues
Classifier: Programming Language :: Python :: 3
Classifier: License :: OSI Approved :: Apache Software License
Classifier: Operating System :: OS Independent
Classifier: Topic :: Scientific/Engineering :: Artificial Intelligence
Requires-Python: >=3.8
License-File: LICENSE
Requires-Dist: torch>=2.0.0
Requires-Dist: transformers>=4.30.0
Requires-Dist: accelerate
Requires-Dist: peft
Requires-Dist: tqdm
Requires-Dist: datasets
Dynamic: license-file
